MANIFEST.in
README
setup.py
epio/__init__.py
epio/client.py
epio.egg-info/PKG-INFO
epio.egg-info/SOURCES.txt
epio.egg-info/dependency_links.txt
epio.egg-info/entry_points.txt
epio.egg-info/requires.txt
epio.egg-info/top_level.txt
epio/commands/__init__.py
epio/commands/create.py
epio/commands/delete.py
epio/commands/django.py
epio/commands/ps.py
epio/commands/resume.py
epio/commands/run.py
epio/commands/run_command.py
epio/commands/set_app.py
epio/commands/suspend.py
epio/commands/upload.py
epio/commands/upload_ssh_key.py
epio/skeleton/epio.ini
epio/ssl/StartCom_CA.pem