Metadata-Version: 1.0
Name: epio
Version: 0.3.1
Summary: The command-line client for the ep.io service
Home-page: http://www.ep.io/
Author: The ep.io Team
Author-email: team@ep.io
License: UNKNOWN
Platform: UNKNOWN
